blue_wallet_client/__init__.py
blue_wallet_client/blue_wallet_client.py
blue_wallet_client/example.py
blue_wallet_client/lightning_address_utils.py
blue_wallet_client-0.0.13.dist-info/METADATA
blue_wallet_client-0.0.13.dist-info/WHEEL
blue_wallet_client-0.0.13.dist-info/licenses/LICENSE
blue_wallet_client-0.0.13.dist-info/RECORD
