Metadata-Version: 2.1
Name: blue_wallet_client
Version: 0.0.13
Summary: Bitcoin lightning wallet for python. A Python client for the API of custodial Bitcoin Lightning wallet called Blue Wallet. 
Project-URL: Homepage, https://github.com/snow884/blue_wallet_client
Project-URL: Bug Tracker, https://github.com/snow884/blue_wallet_client/issues
Author-email: Adam Ivansky <adam.ivansky@gmail.com>
License-File: LICENSE
Classifier: License :: OSI Approved :: MIT License
Classifier: Operating System :: OS Independent
Classifier: Programming Language :: Python :: 3
Requires-Python: >=3.7
Requires-Dist: requests>=2.6.1
